{
    "default" : {
        "dnn_hidden_units": "100",
        "learning_rate" : 0.002,
         "max_steps" :  1500,
         "batch_size":  200,
         "weight_init":  "normal",
         "weight_init_scale":  0.0001,
         "weight_reg": "l2",
         "weight_reg_strength":  0.0,
         "dropout_rate":  0.0,
         "activation": "relu",
         "optimizer":  "sgd",
         "grad_clipping": false  },

    "default_adam_normal_l2" : {
        "dnn_hidden_units": "100",
        "learning_rate" : 0.0003,
         "max_steps" :  1500,
         "batch_size":  256,
         "weight_init":  "normal",
         "weight_init_scale":  0.001,
         "weight_reg": "l2",
         "weight_reg_strength":  0.00005,
         "dropout_rate":  0.4,
         "activation": "relu",
         "optimizer":  "adam",
         "grad_clipping": true  },

    "default_adam_normal_l1" : {
        "dnn_hidden_units": "100",
        "learning_rate" : 0.0003,
         "max_steps" :  1500,
         "batch_size":  256,
         "weight_init":  "normal",
         "weight_init_scale":  0.001,
         "weight_reg": "l1",
         "weight_reg_strength":  0.00005,
         "dropout_rate":  0.4,
         "activation": "relu",
         "optimizer":  "adam",
         "grad_clipping": true  },

    "moreunits_adam_normal_l2" : {
        "dnn_hidden_units": "300,200",
        "learning_rate" : 0.0003,
         "max_steps" :  1500,
         "batch_size":  256,
         "weight_init":  "normal",
         "weight_init_scale":  0.001,
         "weight_reg": "l2",
         "weight_reg_strength":  0.00005,
         "dropout_rate":  0.4,
         "activation": "relu",
         "optimizer":  "adam",
         "grad_clipping": true  },

    "moreunits_adam_normal_l2_elu" : {
        "dnn_hidden_units": "300,200",
        "learning_rate" : 0.0003,
         "max_steps" :  1500,
         "batch_size":  256,
         "weight_init":  "normal",
         "weight_init_scale":  0.001,
         "weight_reg": "l2",
         "weight_reg_strength":  0.00005,
         "dropout_rate":  0.4,
         "activation": "elu",
         "optimizer":  "adam",
         "grad_clipping": true  },

    "moreunits_adam_xavier_l2" : {
        "dnn_hidden_units": "300,200",
        "learning_rate" : 0.0003,
         "max_steps" :  1500,
         "batch_size":  256,
         "weight_init":  "xavier",
         "weight_init_scale":  0.001,
         "weight_reg": "l2",
         "weight_reg_strength":  0.00005,
         "dropout_rate":  0.4,
         "activation": "relu",
         "optimizer":  "adam",
         "grad_clipping": true  },

    "moreunits_adam_xavier_l2_6Ksteps" : {
        "dnn_hidden_units": "300,200",
        "learning_rate" : 0.0003,
         "max_steps" :  6000,
         "batch_size":  256,
         "weight_init":  "xavier",
         "weight_init_scale":  0.001,
         "weight_reg": "l2",
         "weight_reg_strength":  0.00005,
         "dropout_rate":  0.4,
         "activation": "relu",
         "optimizer":  "adam",
         "grad_clipping": true  },

    "deep_adam_xavier_l2" : {
        "dnn_hidden_units": "300,200,200,100",
        "learning_rate" : 0.0003,
         "max_steps" :  6000,
         "batch_size":  256,
         "weight_init":  "xavier",
         "weight_init_scale":  0.001,
         "weight_reg": "l2",
         "weight_reg_strength":  0.0005,
         "dropout_rate":  0.6,
         "activation": "relu",
         "optimizer":  "adam",
         "grad_clipping": true  },


    "deep_adam_xavier_l2" : {
        "dnn_hidden_units": "300,200,200,100",
        "learning_rate" : 0.0003,
         "max_steps" :  6000,
         "batch_size":  256,
         "weight_init":  "normal",
         "weight_init_scale":  0.001,
         "weight_reg": "l2",
         "weight_reg_strength":  0.0005,
         "dropout_rate":  0.6,
         "activation": "relu",
         "optimizer":  "adam",
         "grad_clipping": true  }

}